fairotrials_validators-0.1.0.dist-info/licenses/LICENSE
validators/__init__.py
validators/accessible_link_checker.py
validators/cli.py
validators/consort_harms_validator.py
validators/data_sharing_validator.py
validators/fair_metadata_validator.py
validators/fdaaa_timeliness_validator.py
validators/linkage_validator.py
validators/outcome_switching_validator.py
fairotrials_validators-0.1.0.dist-info/METADATA
fairotrials_validators-0.1.0.dist-info/WHEEL
fairotrials_validators-0.1.0.dist-info/entry_points.txt
fairotrials_validators-0.1.0.dist-info/top_level.txt
fairotrials_validators-0.1.0.dist-info/RECORD
