Metadata-Version: 2.4
Name: fairotrials-validators
Version: 0.1.0
Summary: Seven MVP validators for clinical-trial transparency and traceability (POSE Phase I demo).
Author-email: "Matt Vassar et al." <placeholder@example.com>
License: Apache-2.0
Classifier: Programming Language :: Python :: 3
Classifier: License :: OSI Approved :: Apache Software License
Classifier: Operating System :: OS Independent
Requires-Python: >=3.10
License-File: LICENSE
Dynamic: license-file
